ct_redis_cache_lib/__init__.py
ct_redis_cache_lib/cache.py
qwertyuiop-0.0.4.dist-info/METADATA
qwertyuiop-0.0.4.dist-info/WHEEL
qwertyuiop-0.0.4.dist-info/top_level.txt
qwertyuiop-0.0.4.dist-info/RECORD
