Metadata-Version: 2.4
Name: qwertyuiop
Version: 0.0.4
Summary: A specialized library developed by Credenti for efficient Redis caching in Flask applications.
Author: credenti
Author-email: mgude@credenti.io
Requires-Dist: redis==5.2.0
Requires-Dist: Flask>=3.0.3
Dynamic: author
Dynamic: author-email
Dynamic: description
Dynamic: description-content-type
Dynamic: requires-dist
Dynamic: summary
